similaripy/__init__.py
similaripy/normalization.py
similaripy/similarity.py
similaripy/utility.py
similaripy/cython_code/__init__.py
similaripy/cython_code/coo_to_csr.h
similaripy/cython_code/normalization.cpp
similaripy/cython_code/normalization.cpython-37m-darwin.so
similaripy/cython_code/normalization.pyx
similaripy/cython_code/s_plus.cpp
similaripy/cython_code/s_plus.cpython-37m-darwin.so
similaripy/cython_code/s_plus.h
similaripy/cython_code/s_plus.pyx
similaripy-0.1.1.dist-info/LICENSE
similaripy-0.1.1.dist-info/METADATA
similaripy-0.1.1.dist-info/WHEEL
similaripy-0.1.1.dist-info/top_level.txt
similaripy-0.1.1.dist-info/RECORD
