Metadata-Version: 2.1
Name: similaripy
Version: 0.1.1
Summary: Fast KNN Similarity Algorithms for Collaborative Filtering Models using sparse matrices
Home-page: http://github.com/bogliosimone/similaripy
Author: Simone Boglio
Author-email: bogliosimone@gmail.com
License: MIT
Keywords: Similarity,KNN,Nearest Neighbors,Collaborative Filtering,Normalization,Recommender Systems
Platform: UNKNOWN
Classifier: Development Status :: 4 - Beta
Classifier: Natural Language :: English
Classifier: Intended Audience :: Science/Research
Classifier: License :: OSI Approved :: MIT License
Classifier: Programming Language :: Python
Classifier: Programming Language :: Python :: 3
Classifier: Programming Language :: Python :: 3.4
Classifier: Programming Language :: Python :: 3.5
Classifier: Programming Language :: Python :: 3.6
Classifier: Programming Language :: Python :: 3.7
Classifier: Programming Language :: Cython
Classifier: Operating System :: OS Independent
Classifier: Topic :: Software Development :: Libraries :: Python Modules
Requires-Dist: scipy (>=1.0.0)
Requires-Dist: numpy (>=1.14.0)
Requires-Dist: tqdm (>=4.19.6)
